README.md
setup.py
sfdc_api/__init__.py
sfdc_api/errors.py
sfdc_api/session.py
sfdc_api.egg-info/PKG-INFO
sfdc_api.egg-info/SOURCES.txt
sfdc_api.egg-info/dependency_links.txt
sfdc_api.egg-info/top_level.txt
sfdc_api/metadata/__init__.py
sfdc_api/metadata/metadata.py
sfdc_api/query/__init__.py
sfdc_api/query/query.py
sfdc_api/sobjects/__init__.py
sfdc_api/sobjects/sobjects.py
sfdc_api/tooling/__init__.py
sfdc_api/tooling/runtests.py
sfdc_api/tooling/sobjects.py
sfdc_api/tooling/tooling.py
sfdc_api/utils/__init__.py
sfdc_api/utils/connection.py
sfdc_api/utils/constants.py
sfdc_api/utils/soap.py
sfdc_api/utils/string_utils.py
sfdc_api/wsdl/__init__.py
sfdc_api/wsdl/wsdl.py