Metadata-Version: 1.1
Name: sfdc-api
Version: 0.1.dev5
Summary: A Salesforce API wrapper focused on a zero dependency development workflow
Home-page: UNKNOWN
Author: UNKNOWN
Author-email: UNKNOWN
License: MIT
Download-URL: https://github.com/FernandoPicazo/sfdc_api.git
Platform: UNKNOWN
